[
  {
    "Name": "Wuthering Heights",
    "Author": {
      "Name": "Emily",
      "Surname": "Bronte"
    },
    "Category": "tragedy",
    "Language": "english",
    "PublicationDate": "1847",
    "ISBN": "29256"
  },
  {
    "Name": "The Call of the Wild",
    "Author": {
      "Name": "Jack",
      "Surname": "London"
    },
    "Category": "adventure",
    "Language": "english",
    "PublicationDate": "1903",
    "ISBN": "29257"
  },
  {
    "Name": "Alice's Adventures in Wonderland",
    "Author": {
      "Name": "Lewis",
      "Surname": "Carroll"
    },
    "Category": "fantasy",
    "Language": "english",
    "PublicationDate": "1865",
    "ISBN": "29456"
  }
  //,
 // {
//    "NAME": "A CHRISTMAS CAROL",
//    "AUTHOR": [
//      "CHARLES DICKENS"
//    ],
//    "CATEGORY": [
//      "FANTASY"
//    ],
//    "LANGUAGE": "ENGLISH",
//    "PUBLICATIONDATE": "1843",
//    "ISBN": "13254"
//  },
//  {
//    "Name": "Oliver Twist",
//    "Author": [
//      "Charles Dickens"
//    ],
//    "Category": [
//      "Adventure"
//    ],
//    "Language": "English",
//    "PublicationDate": "1838",
//    "ISBN": "277854"
//  },
//  {
//    "Name": "David Copperfield",
//    "Author": [
//      "Charles Dickens"
//    ],
//    "Category": [
//      "Adventure"
//    ],
//    "Language": "English",
//    "PublicationDate": "1848",
//    "ISBN": "277994"
//  },
//  {
//    "Name": "The Pickwick Papers",
//    "Author": [
//      "Charles Dickens"
//    ],
//    "Category": [
//      "Adventure"
//    ],
//    "Language": "English",
//    "PublicationDate": "1836",
//    "ISBN": "277921"
//  },
//  {
//    "Name": "The Great Gatsby",
//    "Author": [
//      "Scott Fitzgerald"
//    ],
//    "Category": [
//      "Tragedy"
//    ],
//    "Language": "English",
//    "PublicationDate": "1925",
//    "ISBN": "277876"
//  },
//  {
//    "Name": "Tender Is the Night",
//    "Author": [
//      "Scott Fitzgerald"
//    ],
//    "Category": [
//      "Romance"
//    ],
//    "Language": "English",
//    "PublicationDate": "1925",
//    "ISBN": "2709076"
//  },
//  {
//    "Name": "The Curious Case of Benjamin Button",
//    "Author": [
//      "Scott Fitzgerald"
//    ],
//    "Category": [
//      "Romance",
//      "Fantasy"
//    ],
//    "Language": "English",
//    "PublicationDate": "1922",
//    "ISBN": "2709006"
//  },
//  {
//    "Name": "To Kill a Mockingbird",
//    "Author": [
//      "Harper Leed"
//    ],
//    "Category": [
//      "Drama"
//    ],
//    "Language": "English",
//    "PublicationDate": "1960",
//    "ISBN": "2709010"
//  },
//  {
//    "Name": "Moby-Dick",
//    "Author": [
//      "Herman Melville"
//    ],
//    "Category": [
//      "Adventure"
//    ],
//    "Language": "English",
//    "PublicationDate": "1851",
//    "ISBN": "5609010"
//  },
//  {
//    "Name": "White-Jacket",
//    "Author": [
//      "Herman Melville"
//    ],
//    "Category": [
//      "Adventure"
//    ],
//    "Language": "English",
//    "PublicationDate": "1850",
//    "ISBN": "5609011"
//  },
//  {
//    "Name": "The Dead Zone",
//    "Author": [
//      "Stephen King"
//    ],
//    "Category": [
//      "Science",
//      "Fiction",
//      "Thriller"
//    ],
//    "Language": "English",
//    "PublicationDate": "1979",
//    "ISBN": "5624011"
//  },
//  {
//    "Name": "Pet Sematary",
//    "Author": [
//      "Stephen King"
//    ],
//    "Category": [
//      "Horror"
//    ],
//    "Language": "English",
//    "PublicationDate": "1983",
//    "ISBN": "5609081"
//  },
//  {
//    "Name": "It",
//    "Author": [
//      "Stephen King"
//    ],
//    "Category": [
//      "Horror",
//      "Fiction",
//      "Thriller"
//    ],
//    "Language": "English",
//    "PublicationDate": "1983",
//    "ISBN": "5622081"
//  },
//  {
//    "Name": "The Tommyknockers",
//    "Author": [
//      "Stephen King"
//    ],
//    "Category": [
//      "Science",
//      "Fiction"
//    ],
//    "Language": "German",
//    "PublicationDate": "1987",
//    "ISBN": "55522081"
//  },
//  {
//    "Name": "Bag of Bones",
//    "Author": [
//      "Stephen King"
//    ],
//    "Category": [
//      "Horror"
//    ],
//    "Language": "German",
//    "PublicationDate": "1998",
//    "ISBN": "5552881"
//  },
//  {
//    "Name": "Kakė Makė ir Supertėčio diena",
//    "Author": [
//      "Lina Matiukaite"
//    ],
//    "Category": [
//      "Adventure",
//      "Fantasy"
//    ],
//    "Language": "Lithuanian",
//    "PublicationDate": "2012",
//    "ISBN": "55512381"
//  },
//  {
//    "Name": "KKakė Makė ir didelė Tamsa",
//    "Author": [
//      "Lina Matiukaite"
//    ],
//    "Category": [
//      "Adventure",
//      "Fantasy"
//    ],
//    "Language": "Lithuanian",
//    "PublicationDate": "2013",
//    "ISBN": "5551271"
//  },
//  {
//    "Name": "Kakė Makė ir didelė Tamsa",
//    "Author": [
//      "Lina Matiukaite"
//    ],
//    "Category": [
//      "Adventure",
//      "Fantasy"
//    ],
//    "Language": "Lithuanian",
//    "PublicationDate": "2015",
//    "ISBN": "55513981"
//  }
]
